{
  "updated_at": 1774137282,
  "active_session_id": "019d12cf-0aba-71d0-8920-5ea920811f62",
  "current_focus": "Treat K=128 only as the initial search anchor, not as a success criterion. The research objective is to find configurations whose FVU is dramatically better than the current K=128 baseline, with a target on the order of halving that baseline FVU before rewarding smaller K or lower cost.",
  "best_full_frontier": {
    "128": {
      "fvu": 0.13607123959809542,
      "architecture": "two_stage_residual",
      "commit": "da03f9c23713fe6e646d448701fe35472f5c8545",
      "config": {
        "architecture": "two_stage_residual",
        "expansion_factor": 16,
        "k": 128,
        "optimizer": "signum",
        "lr": "1.6e-3",
        "hookpoints": "layers.[3].self_attn.o_proj",
        "batch_size": 1,
        "grad_acc_steps": 8,
        "micro_acc_steps": 1,
        "auxk_alpha": 0.0,
        "dead_feature_threshold": 10000000,
        "use_hadamard": false,
        "tier": "full",
        "family_name": "two_stage_residual",
        "family_stage": "stabilize"
      },
      "tier": "full",
      "checkpoint": "/root/sparsify-ascend/checkpoints/research_agent/round_0010_full/round0010_full_1774134040_dp2_bs1_ga8_ef16_k128_20260322_070046",
      "peak_memory_gb": null
    },
    "64": {
      "fvu": 0.20609215833246708,
      "architecture": "gated",
      "commit": "38e1e63bf3f94951decb6db7632a5e05a963756b",
      "config": {
        "architecture": "gated",
        "expansion_factor": 16,
        "k": 64,
        "optimizer": "signum",
        "lr": "1.6e-3",
        "hookpoints": "layers.[3].self_attn.o_proj",
        "batch_size": 1,
        "grad_acc_steps": 8,
        "micro_acc_steps": 1,
        "auxk_alpha": 0.0,
        "dead_feature_threshold": 10000000,
        "use_hadamard": false,
        "tier": "full",
        "family_name": "gated",
        "family_stage": "stabilize"
      },
      "tier": "full",
      "checkpoint": "/root/sparsify-ascend/checkpoints/research_agent/round_0060_full/round0060_full_1774102938_dp2_bs1_ga8_ef16_k64_20260321_222228",
      "peak_memory_gb": null
    },
    "32": {
      "fvu": 0.2587709631770849,
      "architecture": "gated",
      "commit": "3e3db0477289cd7015c99e22168919ed2cbcbca0",
      "config": {
        "architecture": "gated",
        "expansion_factor": 16,
        "k": 32,
        "optimizer": "signum",
        "lr": "1.6e-3",
        "hookpoints": "layers.[3].self_attn.o_proj",
        "batch_size": 1,
        "grad_acc_steps": 8,
        "micro_acc_steps": 1,
        "auxk_alpha": 0.0,
        "dead_feature_threshold": 10000000,
        "use_hadamard": false,
        "tier": "full",
        "family_name": "gated",
        "family_stage": "stabilize"
      },
      "tier": "full",
      "checkpoint": "/root/sparsify-ascend/checkpoints/research_agent/round_0064_full/round0064_full_1774104027_dp2_bs1_ga8_ef16_k32_20260321_224037",
      "peak_memory_gb": null
    }
  },
  "pareto_full_frontier": [
    {
      "k": 32,
      "fvu": 0.2587709631770849,
      "architecture": "gated",
      "commit": "3e3db0477289cd7015c99e22168919ed2cbcbca0",
      "config": {
        "architecture": "gated",
        "expansion_factor": 16,
        "k": 32,
        "optimizer": "signum",
        "lr": "1.6e-3",
        "hookpoints": "layers.[3].self_attn.o_proj",
        "batch_size": 1,
        "grad_acc_steps": 8,
        "micro_acc_steps": 1,
        "auxk_alpha": 0.0,
        "dead_feature_threshold": 10000000,
        "use_hadamard": false,
        "tier": "full",
        "family_name": "gated",
        "family_stage": "stabilize"
      },
      "tier": "full",
      "checkpoint": "/root/sparsify-ascend/checkpoints/research_agent/round_0064_full/round0064_full_1774104027_dp2_bs1_ga8_ef16_k32_20260321_224037",
      "peak_memory_gb": null
    },
    {
      "k": 64,
      "fvu": 0.20609215833246708,
      "architecture": "gated",
      "commit": "38e1e63bf3f94951decb6db7632a5e05a963756b",
      "config": {
        "architecture": "gated",
        "expansion_factor": 16,
        "k": 64,
        "optimizer": "signum",
        "lr": "1.6e-3",
        "hookpoints": "layers.[3].self_attn.o_proj",
        "batch_size": 1,
        "grad_acc_steps": 8,
        "micro_acc_steps": 1,
        "auxk_alpha": 0.0,
        "dead_feature_threshold": 10000000,
        "use_hadamard": false,
        "tier": "full",
        "family_name": "gated",
        "family_stage": "stabilize"
      },
      "tier": "full",
      "checkpoint": "/root/sparsify-ascend/checkpoints/research_agent/round_0060_full/round0060_full_1774102938_dp2_bs1_ga8_ef16_k64_20260321_222228",
      "peak_memory_gb": null
    },
    {
      "k": 128,
      "fvu": 0.13607123959809542,
      "architecture": "two_stage_residual",
      "commit": "da03f9c23713fe6e646d448701fe35472f5c8545",
      "config": {
        "architecture": "two_stage_residual",
        "expansion_factor": 16,
        "k": 128,
        "optimizer": "signum",
        "lr": "1.6e-3",
        "hookpoints": "layers.[3].self_attn.o_proj",
        "batch_size": 1,
        "grad_acc_steps": 8,
        "micro_acc_steps": 1,
        "auxk_alpha": 0.0,
        "dead_feature_threshold": 10000000,
        "use_hadamard": false,
        "tier": "full",
        "family_name": "two_stage_residual",
        "family_stage": "stabilize"
      },
      "tier": "full",
      "checkpoint": "/root/sparsify-ascend/checkpoints/research_agent/round_0010_full/round0010_full_1774134040_dp2_bs1_ga8_ef16_k128_20260322_070046",
      "peak_memory_gb": null
    }
  ],
  "recent_results": [
    {
      "experiment_id": "proxy_1774135933",
      "tier": "proxy",
      "status": "ok",
      "decision": "incubate",
      "val_fvu": "0.25158748403191566",
      "k": "128",
      "architecture": "multi_branch_gated",
      "description": "Run a `multi_branch_gated` proxy stabilization pass at K=128 with `EXPANSION_FACTOR=32`, keeping the current signum/aux-free recipe fixed and changing only expansion factor."
    },
    {
      "experiment_id": "proxy_1774136942",
      "tier": "proxy",
      "status": "ok",
      "decision": "incubate",
      "val_fvu": "0.15793968923389912",
      "k": "128",
      "architecture": "multi_branch_gated",
      "description": "Edit `multi_branch_gated` to use a simpler two-branch default routing structure, then run a proxy comparison at K=128 with the current signum/EF=16/aux-free recipe, changing only that family-specific branch-count parameter."
    },
    {
      "experiment_id": "proxy_1774137281",
      "tier": "proxy",
      "status": "ok",
      "decision": "discard",
      "val_fvu": "0.19914506003260612",
      "k": "128",
      "architecture": "two_stage_residual",
      "description": "Run a proxy sweep point for `two_stage_residual` at K=128 with `LR=4e-4`, holding the rest of the best recipe fixed (`ARCHITECTURE=two_stage_residual`, `EXPANSION_FACTOR=16`, `OPTIMIZER=signum`, `AUXK_ALPHA=0.0`). This is a one-variable exploitation pass aligned with the policy's prescribed untested LR set."
    }
  ],
  "recent_round_summaries": [
    {
      "round": 65,
      "family_name": "gated",
      "family_stage": "stabilize",
      "duration_sec": 533,
      "hypothesis": "The gated family has now exhausted the standard signum-side LR, aux, expansion, and low-K sweeps, while the research objective still needs a materially better K=128-quality signal. The least-bad next exploitation move is to keep the best gated K=128, EF=16, `AUXK_ALPHA=0` recipe fixed and change only the optimizer from `signum` to `adam` to test whether a different optimization dynamic can break through the current quality plateau without introducing new architectural risk.",
      "change_type": "param_only",
      "experiment_tier": "proxy",
      "decision": "discard",
      "val_fvu": "0.2000631969422102",
      "run_health": "normal",
      "termination_reason": "completed"
    },
    {
      "round": 66,
      "family_name": "jumprelu",
      "family_stage": "stabilize",
      "duration_sec": 143,
      "hypothesis": "The gated family now appears locally exhausted: the aux, LR, expansion, low-K, and optimizer sweeps have not moved the K=128 full frontier, and the recent `adam` trial regressed badly in full despite a decent proxy. The least-bad next informative move is to switch the single primary variable back to architecture and re-benchmark the strongest alternative promoted family, `jumprelu`, at K=128 under the current strongest shared training regime to\n[truncated for compact history]",
      "change_type": "param_only",
      "experiment_tier": "proxy",
      "decision": "incubate",
      "val_fvu": "0.2653468679636717",
      "run_health": "normal",
      "termination_reason": "completed"
    },
    {
      "round": 67,
      "family_name": "lowrank_residual",
      "family_stage": "prototype",
      "duration_sec": 194,
      "hypothesis": "The best existing promoted alternatives have now been refreshed and still sit well behind the gated frontier, so the least-bad next informative move is a genuinely new architecture family rather than another local sweep. A `lowrank_residual` SAE that uses a learned low-rank linear trunk plus a sparse residual coder could remove shared dense structure before TopK selection, which is a materially different way to attack the K=128 quality ceiling\n[truncated for compact history]",
      "change_type": "edit_sae_code",
      "experiment_tier": "proxy",
      "decision": "crash",
      "val_fvu": "None",
      "run_health": "crash",
      "termination_reason": "completed"
    }
  ],
  "incubating_families": {
    "jumprelu": {
      "status": "incubating",
      "design_hypothesis": "Five rounds of gated-local tuning have failed to move the frontier, so the current search direction is likely locally exhausted. The least-disruptive fundamentally different probe is to switch the single primary variable back to architecture and run `jumprelu` at K=128 under the strongest shared signum recipe to test whether a different sparse activation mechanism can reopen quality gains without introducing new code risk.",
      "best_proxy_fvu": null,
      "tested_configs": [
        {
          "round": 3,
          "stage": "stabilize",
          "k": "128",
          "decision": "incubate",
          "val_fvu": "0.2653468679636717",
          "run_health": "normal"
        }
      ],
      "next_steps": [
        "If `jumprelu` materially improves proxy FVU, promote it to full and treat it as the main alternative trunk for further stabilization.",
        "If `jumprelu` remains clearly behind gated under the shared strong recipe, the next move should be a different architecture path or a narrow compatibility repair for an incubating family rather than more gated parameter sweeps."
      ],
      "last_round": 3
    },
    "lowrank_residual": {
      "status": "incubating",
      "design_hypothesis": "`lowrank_residual` produced the strongest non-gated proxy among recent architecture pivots, so the next informative move is a narrow family-specific stabilization pass rather than abandoning it after one prototype result. The current trunk rank formula likely underpowers the dense trunk under the strong EF=16 recipe by collapsing to a near-minimal rank, so increasing the default trunk capacity should remove more shared dense structure before sparse residual coding and improve FVU at fixed K=128.",
      "best_proxy_fvu": null,
      "tested_configs": [
        {
          "round": 4,
          "stage": "prototype",
          "k": "128",
          "decision": "incubate",
          "val_fvu": "0.22577644512057304",
          "run_health": "normal"
        },
        {
          "round": 5,
          "stage": "stabilize",
          "k": null,
          "decision": "crash",
          "val_fvu": null,
          "run_health": "crash"
        }
      ],
      "next_steps": [
        "If the stronger-trunk `lowrank_residual` materially improves proxy FVU, keep incubating the family and then explore lower K within this family or promote to full if the gain is large enough.",
        "If quality stays similar but throughput regresses, follow with a targeted `edit_perf_code` round rather than treating the family as architecturally weak.",
        "If the stronger trunk still leaves `lowrank_residual` clearly uncompetitive, pivot to a different fundamentally new architecture family instead of returning to gated-local tuning."
      ],
      "last_round": 5
    },
    "whitened_topk": {
      "status": "incubating",
      "design_hypothesis": "After eight straight no-improve rounds and with gated already mapped at K=32/64/128, the least-bad informative move is a fundamentally different architecture that changes the input geometry rather than doing another local sweep. A `whitened_topk` proxy run at K=128 under the current strongest gated recipe can test whether a learned input preconditioner makes the activation space easier to sparsify and opens a new quality frontier without coupling in optimizer or K changes.",
      "best_proxy_fvu": null,
      "tested_configs": [
        {
          "round": 6,
          "stage": "prototype",
          "k": "128",
          "decision": "incubate",
          "val_fvu": "0.2673991918563843",
          "run_health": "normal"
        }
      ],
      "next_steps": [
        "If `whitened_topk` is materially better than recent non-gated alternatives, keep incubating it with a family-specific stabilization pass before any full request.",
        "If `whitened_topk` is clearly uncompetitive, pivot to another genuinely different architecture mechanism rather than returning to minor gated parameter sweeps.",
        "If quality looks promising but runtime is abnormally slow, follow with an `edit_perf_code` round instead of discarding the family on architecture grounds."
      ],
      "last_round": 6
    }
  },
  "recent_performance_findings": [
    "round 48: family=factorized_topk stage=prototype change=param_only decision=crash fvu=None termination=completed",
    "round 52: family=factorized_topk stage=prototype change=edit_sae_code decision=crash fvu=None termination=identical_to_baseline",
    "round 57: family=residual_topk stage=prototype change=edit_sae_code decision=crash fvu=None termination=completed",
    "round 67: family=lowrank_residual stage=prototype change=edit_sae_code decision=crash fvu=None termination=completed"
  ],
  "recent_sanity_failures": [
    {
      "round": 46,
      "family_name": "factorized_topk",
      "change_type": "edit_perf_code",
      "error_type": "sanity_check_failed",
      "termination_reason": null,
      "error_summary": "  File \"<string>\", line 1\n    import sys; sys.path.insert(0, '.'); from sparsify import SparseCoder; from sparsify.config import SparseCoderConfig; import torch; device = 'cuda' if torch.cuda.is_available() else 'cpu'; try:\n[truncated for compact history]"
    }
  ],
  "recent_training_failures": [
    {
      "round": 61,
      "family_name": "residual_topk",
      "change_type": "edit_sae_code",
      "error_type": "ValueError",
      "termination_reason": "completed",
      "error_summary": "ValueError: Unknown architecture: 'residual_topk'. Must be one of ('topk', 'jumprelu', 'gated', 'routed', 'group_topk', 'factorized_topk')"
    },
    {
      "round": 62,
      "family_name": "residual_topk",
      "change_type": "edit_sae_code",
      "error_type": "ValueError",
      "termination_reason": "completed",
      "error_summary": "ValueError: Unknown architecture: 'residual_topk'. Must be one of ('topk', 'jumprelu', 'gated', 'routed', 'group_topk', 'factorized_topk')"
    },
    {
      "round": 67,
      "family_name": "lowrank_residual",
      "change_type": "edit_sae_code",
      "error_type": "ValueError",
      "termination_reason": "completed",
      "error_summary": "ValueError: Unknown architecture: 'lowrank_residual'. Must be one of ('topk', 'jumprelu', 'gated', 'routed', 'group_topk', 'factorized_topk')"
    },
    {
      "round": 5,
      "family_name": "lowrank_residual",
      "change_type": "edit_sae_code",
      "error_type": "",
      "termination_reason": "identical_to_baseline",
      "error_summary": ""
    }
  ],
  "pending_hints": [],
  "next_move_guidance": [
    "If `LR=4e-4` improves proxy FVU, promote and then continue LR stabilization before changing another parameter.",
    "If `LR=4e-4` regresses, test the remaining prescribed LR extremes (`2e-4` or `3.2e-3`) one at a time before revisiting aux or EF.",
    "If LR sweep stays flat across the prescribed points, move to the next one-variable exploitation axis on this family, likely `AUXK_ALPHA=0.01`."
  ],
  "last_round": 14
}
