{
  "round": 24,
  "timestamp": 1774144042,
  "started_at": 1774143383,
  "ended_at": 1774144042,
  "duration_sec": 659,
  "family_name": "lowrank_gated_residual",
  "family_stage": "stabilize",
  "session_id": "019d130c-782e-75a2-aa6f-506b18d29edf",
  "timeline_start_event_id": "evt_1774143383187345671",
  "timeline_end_event_id": "evt_1774144042182520321",
  "timeline_event_ids": [
    "evt_1774143383187345671",
    "evt_1774143383187514585",
    "evt_1774143500635802868",
    "evt_1774143500635933921",
    "evt_1774143500636254157",
    "evt_1774143530637603825",
    "evt_1774143560638934617",
    "evt_1774143590850053771",
    "evt_1774143591379996785",
    "evt_1774143591380114724",
    "evt_1774143591380566615",
    "evt_1774143621381841587",
    "evt_1774143651383183497",
    "evt_1774143681385109514",
    "evt_1774143711387807839",
    "evt_1774143741390898970",
    "evt_1774143771394568374",
    "evt_1774143801398783367",
    "evt_1774143831403557298",
    "evt_1774143861408920278",
    "evt_1774143891414804757",
    "evt_1774143921656931040",
    "evt_1774143951757749215",
    "evt_1774143981970630209",
    "evt_1774144012094221077",
    "evt_1774144042101772730",
    "evt_1774144042181909187",
    "evt_1774144042181971764",
    "evt_1774144042182520321"
  ],
  "repair_attempts": [],
  "experiment_branch": "autoresearch-sae",
  "experiment_commit_message": "experiment: round 0024 full lowrank_gated_residual keep",
  "proxy_result": {
    "experiment_id": "proxy_1774143591",
    "status": "ok",
    "decision": "promote",
    "val_fvu": "0.1756359562277794",
    "k": "32",
    "architecture": "lowrank_gated_residual",
    "log_path": "/root/sparsify-ascend/research/history/logs/proxy_1774143591.log",
    "termination_reason": "completed",
    "run_health": "normal",
    "tokens_per_sec": "55339.200860",
    "baseline_tokens_per_sec": "66557.551775",
    "baseline_ratio": "0.831449",
    "observed_fvu": "0.174893",
    "proxy_mode": "fast",
    "evaluation_basis": "terminal_only",
    "curve_start_fvu": "0.342404",
    "curve_mid_fvu": "0.221214",
    "curve_end_fvu": "0.174893",
    "curve_late_slope": "-0.000000",
    "curve_still_improving": "true",
    "metrics_path": "/root/sparsify-ascend/checkpoints/research_agent/round_0024_proxy/round0024_proxy_1774143500_dp2_bs1_ga8_ef32_k32_20260322_093829/metrics.jsonl"
  },
  "full_result": {
    "experiment_id": "full_1774144042",
    "status": "ok",
    "decision": "keep",
    "val_fvu": "0.09578194748610258",
    "k": "32",
    "architecture": "lowrank_gated_residual",
    "log_path": "/root/sparsify-ascend/research/history/logs/full_1774144042.log",
    "termination_reason": "completed",
    "run_health": "normal",
    "tokens_per_sec": "88695.605754",
    "baseline_tokens_per_sec": "78283.771310",
    "baseline_ratio": "1.133001",
    "observed_fvu": "0.093657",
    "proxy_mode": "",
    "evaluation_basis": "",
    "curve_start_fvu": "0.132731",
    "curve_mid_fvu": "0.115365",
    "curve_end_fvu": "0.093657",
    "curve_late_slope": "-0.000000",
    "curve_still_improving": "true",
    "metrics_path": "/root/sparsify-ascend/checkpoints/research_agent/round_0024_full/round0024_full_1774143591_dp2_bs1_ga8_ef32_k32_20260322_094000/metrics.jsonl"
  },
  "action": {
    "command": "run",
    "hypothesis": "`lowrank_gated_residual` has now improved the full frontier at both K=128 and K=64, so the next clean move is to change only K again and test whether the family also strengthens the smallest currently active Pareto point. A proxy K=32 run under the same EF=32 signum recipe will show whether the gated residual selector is a general frontier improvement rather than only a medium/high-K gain.",
    "summary": "Run a proxy stabilization pass for `lowrank_gated_residual` at K=32 while holding EF=32, signum, LR=1.6e-3, and AUXK_ALPHA=0 fixed. This directly tests whether the new family can replace `lowrank_residual` across the full current Pareto set by improving the smallest-K point as well.",
    "change_type": "param_only",
    "experiment_tier": "proxy",
    "expected_win": "lower_fvu",
    "family_name": "lowrank_gated_residual",
    "family_stage": "stabilize",
    "self_review": "This keeps the round to one primary variable, `k`, and follows the family-specific stabilization sequence opened by the successful K=128 and K=64 full results. It is the highest-value next check because it can either complete a coherent frontier takeover for the family or cleanly bound where its gains stop.",
    "needs_sanity": false,
    "env_overrides": [
      {
        "key": "ARCHITECTURE",
        "value": "lowrank_gated_residual"
      },
      {
        "key": "K",
        "value": "32"
      },
      {
        "key": "EXPANSION_FACTOR",
        "value": "32"
      },
      {
        "key": "OPTIMIZER",
        "value": "signum"
      },
      {
        "key": "LR",
        "value": "1.6e-3"
      },
      {
        "key": "AUXK_ALPHA",
        "value": "0.0"
      },
      {
        "key": "DEAD_FEATURE_THRESHOLD",
        "value": "10000000"
      },
      {
        "key": "USE_HADAMARD",
        "value": "0"
      }
    ],
    "touched_files": [],
    "notes_to_memory": [
      "Round 24 tests `lowrank_gated_residual` at K=32 after full wins at K=128 and K=64 under the shared EF=32 signum recipe.",
      "This is the next stabilization step needed to determine whether `lowrank_gated_residual` can become the mainline family across the whole current Pareto frontier."
    ],
    "next_hypotheses": [
      "If `lowrank_gated_residual` improves proxy FVU at K=32, promote it to full and treat the family as the leading mainline across K={32,64,128}.",
      "If K=32 is flat or worse, keep `lowrank_gated_residual` as the better family for K>=64 and consider a single-variable internal stabilization move such as `AUXK_ALPHA` within this family.",
      "If K=32 quality is promising but runtime is flagged as a perf regression, follow with a narrow `code_fix` performance pass instead of concluding against the architecture."
    ],
    "primary_variable": "k"
  },
  "result": {
    "experiment_id": "full_1774144042",
    "status": "ok",
    "decision": "keep",
    "val_fvu": "0.09578194748610258",
    "k": "32",
    "architecture": "lowrank_gated_residual",
    "log_path": "/root/sparsify-ascend/research/history/logs/full_1774144042.log",
    "termination_reason": "completed",
    "run_health": "normal",
    "tokens_per_sec": "88695.605754",
    "baseline_tokens_per_sec": "78283.771310",
    "baseline_ratio": "1.133001",
    "observed_fvu": "0.093657",
    "proxy_mode": "",
    "evaluation_basis": "",
    "curve_start_fvu": "0.132731",
    "curve_mid_fvu": "0.115365",
    "curve_end_fvu": "0.093657",
    "curve_late_slope": "-0.000000",
    "curve_still_improving": "true",
    "metrics_path": "/root/sparsify-ascend/checkpoints/research_agent/round_0024_full/round0024_full_1774143591_dp2_bs1_ga8_ef32_k32_20260322_094000/metrics.jsonl"
  },
  "touched_files": [],
  "patch_path": null
}
