{
  "round": 185,
  "timestamp": 1774659984,
  "started_at": 1774659920,
  "ended_at": 1774659984,
  "duration_sec": 64,
  "family_name": "lowrank_two_stage_soft_codebook_residual",
  "family_stage": "mainline",
  "session_id": "019d31ee-e4b2-7823-8cd0-26c946513da2",
  "timeline_event_ids": [
    "evt_1774659920413490368"
  ],
  "repair_attempts": [],
  "experiment_branch": "autoresearch-sae",
  "action": {
    "command": "run",
    "hypothesis": "\u6700\u7ec8\u91cd\u6784\u516c\u5f0f\u4fdd\u6301\u4e3a x_hat = U(Vx) + \u03a3_m pi_m c_m + \u03a3_i alpha_i^(1) b_i + \u03a3_j alpha_j^(2) b_j\uff1b\u5176\u4e2d low-rank trunk \u5e93 U\u3001\u9759\u6001 soft-codebook \u5e93 {c_m}\u3001\u4ee5\u53ca\u4e24\u9636\u6bb5 residual \u5b57\u5178\u5e93 {b_i} \u90fd\u53ef\u9759\u6001\u5bfc\u51fa\uff0c\u56e0\u6b64\u53ef\u76f4\u63a5\u6620\u5c04\u5230 LUTurbo/Lottable \u7684\u201c\u67e5\u8868 + \u52a0\u6743\u6c42\u548c + \u9009\u62e9\u6027\u8865\u507f\u201d\u63a8\u7406\u94fe\u8def\uff0c\u517c\u5bb9\u6027\u5224\u65ad\u4e3a\u6269\u5c55\u517c\u5bb9\u3002\u5f53\u524d\u4e3b\u7ebf\u5728 EF=2 \u4e0b encoder selection_cost \u4ecd\u5728 1.5\u00d7h\u00d7n \u786c\u7ea6\u675f\u5185\uff0c\u4e14\u8fde\u7eed 3 \u8f6e\u56f4\u7ed5 `NUM_CODES` \u538b\u7f29\u90fd\u6ca1\u6709\u6539\u53d8\u66f2\u7ebf\u7ec8\u70b9\uff0c\u8bf4\u660e\u5f53\u524d\u74f6\u9888\u66f4\u53ef\u80fd\u5728\u4f18\u5316\u52a8\u6001\u800c\u4e0d\u662f coarse codebook \u5bb9\u91cf\u3002\u672c\u8f6e\u53ea\u56de\u7b54\u4e00\u4e2a\u95ee\u9898\uff1a\u628a\u4e3b\u53d8\u91cf\u5207\u5230 `optimizer`\uff0c\u5e76\u4f7f\u7528\u66f4\u4fdd\u5b88\u7684 `adam@1.0e-3`\uff0c\u662f\u5426\u80fd\u5728\u4e0d\u6539\u53d8 family/EF/K \u7684\u524d\u63d0\u4e0b\u6539\u5584\u8bad\u7ec3\u66f2\u7ebf\u5f62\u72b6\u6216\u7ec8\u70b9 FVU\uff0c\u800c\u4e0d\u662f\u7ee7\u7eed\u5728 signum \u914d\u65b9\u5468\u56f4\u5f97\u5230\u540c\u6837\u7684 plateau\u3002",
    "summary": "\u505c\u6b62\u7ee7\u7eed\u7ec6\u626b `NUM_CODES`\uff0c\u56de\u5230\u540c\u4e00\u4e3b\u7ebf family \u7684 recipe \u8f74\uff1b\u56fa\u5b9a `ARCHITECTURE=lowrank_two_stage_soft_codebook_residual, K=128, EF=2`\uff0c\u5c06\u4e3b\u53d8\u91cf\u5207\u5230 `optimizer`\uff0c\u6d4b\u8bd5 `adam` \u914d\u5408\u66f4\u4fdd\u5b88\u7684 `LR=1.0e-3` \u662f\u5426\u80fd\u6253\u7834\u5f53\u524d signum \u4e3b\u7ebf\u7684\u6536\u655b\u5e73\u53f0\u3002",
    "change_type": "param_only",
    "expected_win": "information_gain",
    "family_name": "lowrank_two_stage_soft_codebook_residual",
    "family_stage": "mainline",
    "self_review": "\u672c\u8f6e\u4fdd\u6301\u540c\u4e00 family\uff0c\u4e0d\u5f00\u65b0\u67b6\u6784\uff0c\u5e76\u628a\u95ee\u9898\u4ece\u5df2\u7ecf\u53cd\u590d\u65e0\u589e\u76ca\u7684 codebook \u5bb9\u91cf\u8f74\u8f6c\u56de recipe \u8f74\uff0c\u7b26\u5408\u5f53\u524d\u201c\u5148\u628a\u540c\u4e00 family \u7684\u8bad\u7ec3\u66f2\u7ebf\u770b\u6e05\u201d\u7684\u8981\u6c42\u3002\u867d\u7136 `optimizer` \u8f74\u8054\u52a8\u4e86\u66f4\u4fdd\u5b88\u7684 `LR=1.0e-3`\uff0c\u4f46\u8fd9\u5c5e\u4e8e\u907f\u514d\u7528 signum \u5b66\u4e60\u7387\u8bef\u5224 adam \u7684\u5fc5\u8981\u5c40\u90e8\u914d\u5957\uff1b\u4e3b\u95ee\u9898\u4ecd\u7136\u53ea\u6709\u4e00\u4e2a\uff1a\u5f53\u524d\u5e73\u53f0\u662f\u5426\u4e3b\u8981\u6765\u81ea\u4f18\u5316\u5668\u52a8\u6001\u3002",
    "needs_sanity": false,
    "env_overrides": [
      {
        "key": "ARCHITECTURE",
        "value": "lowrank_two_stage_soft_codebook_residual"
      },
      {
        "key": "EXPANSION_FACTOR",
        "value": "2"
      },
      {
        "key": "K",
        "value": "128"
      },
      {
        "key": "OPTIMIZER",
        "value": "adam"
      },
      {
        "key": "LR",
        "value": "1.0e-3"
      }
    ],
    "touched_files": [],
    "notes_to_memory": [
      "family \u4e0e\u5bfc\u51fa\u8def\u5f84\u4e0d\u53d8\uff0c`lowrank_two_stage_soft_codebook_residual` \u4ecd\u662f\u6269\u5c55\u517c\u5bb9\uff1atrunk \u5e93 + soft-codebook \u5e93 + two-stage residual \u5b57\u5178\u5e93\u3002",
      "\u8fde\u7eed 3 \u8f6e `NUM_CODES` \u538b\u7f29\u6ca1\u6709\u6539\u53d8\u7ec8\u70b9 FVU\uff0c\u8bf4\u660e\u5f53\u524d\u4e3b\u7ebf\u66f4\u503c\u5f97\u4f18\u5148\u6f84\u6e05 optimizer/curve-shape \u95ee\u9898\uff0c\u800c\u4e0d\u662f\u7ee7\u7eed\u6cbf coarse codebook \u5bb9\u91cf\u8f74\u4e0b\u63a2\u3002",
      "\u8bc4\u4f30\u672c\u8f6e\u5fc5\u987b\u540c\u65f6\u6bd4\u8f83 curve_start/mid/end\u3001tokens_per_sec\u3001\u603b\u8017\u65f6\u4e0e final_total_tokens\uff0c\u5224\u65ad\u6536\u76ca\u662f\u5426\u6765\u81ea\u66f4\u4f18\u4f18\u5316\u52a8\u6001\uff0c\u800c\u4e0d\u662f\u66f4\u957f\u8bad\u7ec3\u6216\u8fd0\u884c\u65f6\u6ce2\u52a8\u3002"
    ],
    "next_hypotheses": [
      "\u82e5 `adam@1.0e-3` \u66f2\u7ebf\u66f4\u5e73\u6ed1\u4e14\u7ec8\u70b9\u4f18\u4e8e\u6216\u63a5\u8fd1 signum \u4e3b\u7ebf\uff0c\u5219\u7ed9 adam \u4e00\u6b21\u540c\u8f74 LR callback\uff0c\u4f8b\u5982 `1.5e-3`\u3002",
      "\u82e5 `adam@1.0e-3` \u660e\u663e\u66f4\u5dee\u6216\u66f4\u6162\uff0c\u5219\u5173\u95ed optimizer \u5206\u652f\uff0c\u6062\u590d signum \u4e3b\u7ebf\uff0c\u5e76\u56de\u5230 `TRUNK_RANK` \u6216 `NUM_CODES` \u7684\u6210\u672c\u8f74\u3002",
      "\u82e5\u7ec8\u70b9\u63a5\u8fd1\u4f46\u541e\u5410\u660e\u663e\u66f4\u5dee\uff0c\u5219\u5c06 adam \u89c6\u4e3a\u8d1f\u9762\u7cfb\u7edf\u4fe1\u53f7\uff0c\u5373\u4f7f\u5176\u6570\u503c\u6307\u6807\u4e0d\u5dee\u3002"
    ],
    "primary_variable": "optimizer"
  },
  "result": {
    "decision": "policy_reject",
    "status": "policy_reject",
    "timestamp": "1774659984",
    "run_health": "normal",
    "termination_reason": "param_only \u4e00\u6b21\u53ea\u80fd\u6539\u4e00\u4e2a\u4e3b\u8f74\uff1b\u5f53\u524d\u540c\u65f6\u6539\u4e86 optimizer, lr",
    "description": "param_only \u4e00\u6b21\u53ea\u80fd\u6539\u4e00\u4e2a\u4e3b\u8f74\uff1b\u5f53\u524d\u540c\u65f6\u6539\u4e86 optimizer, lr",
    "self_review": ""
  },
  "touched_files": [],
  "patch_path": null
}
